pybuilder_pypi_server/__init__.py
pybuilder_pypi_server/version.py
pybuilder_pypi_server-1.1.0.dist-info/DESCRIPTION.rst
pybuilder_pypi_server-1.1.0.dist-info/METADATA
pybuilder_pypi_server-1.1.0.dist-info/RECORD
pybuilder_pypi_server-1.1.0.dist-info/WHEEL
pybuilder_pypi_server-1.1.0.dist-info/metadata.json
pybuilder_pypi_server-1.1.0.dist-info/namespace_packages.txt
pybuilder_pypi_server-1.1.0.dist-info/top_level.txt
pybuilder_pypi_server-1.1.0.dist-info/zip-safe
