Metadata-Version: 2.0
Name: pybuilder-pypi-server
Version: 1.1.0
Summary: PyBuilder Pipy Server Plugin
Home-page: https://github.com/AlexeySanko/pybuilder_pypi_server
Author: Alexey Sanko
Author-email: alexeycount@gmail.com
License: Apache License, Version 2.0
Platform: UNKNOWN
Classifier: Development Status :: 4 - Beta
Classifier: Environment :: Console
Classifier: Intended Audience :: Developers
Classifier: License :: OSI Approved :: Apache Software License
Classifier: Programming Language :: Python
Classifier: Programming Language :: Python :: 2
Classifier: Programming Language :: Python :: 2.7
Classifier: Programming Language :: Python :: 3
Classifier: Programming Language :: Python :: 3.2
Classifier: Programming Language :: Python :: 3.3
Classifier: Programming Language :: Python :: 3.4
Classifier: Programming Language :: Python :: 3.5
